flask_emails/__init__.py
flask_emails/backends.py
flask_emails/config.py
flask_emails/message.py
flask_emails-0.4.dist-info/DESCRIPTION.rst
flask_emails-0.4.dist-info/METADATA
flask_emails-0.4.dist-info/metadata.json
flask_emails-0.4.dist-info/RECORD
flask_emails-0.4.dist-info/top_level.txt
flask_emails-0.4.dist-info/WHEEL
