Metadata-Version: 2.0
Name: flask-emails
Version: 0.4
Summary: Elegant and simple email library for Flask.
Home-page: https://github.com/lavr/flask-emails
Author: Sergey Lavrinenko
Author-email: s@lavr.me
License: Apache License
Requires-Dist: emails
